django_websocket_request-0.1.1.dist-info/DESCRIPTION.rst
django_websocket_request-0.1.1.dist-info/METADATA
django_websocket_request-0.1.1.dist-info/pydist.json
django_websocket_request-0.1.1.dist-info/RECORD
django_websocket_request-0.1.1.dist-info/top_level.txt
django_websocket_request-0.1.1.dist-info/WHEEL
wsrequest/__init__.py
wsrequest/tests.py
wsrequest/__pycache__/__init__.cpython-33.pyc
wsrequest/__pycache__/tests.cpython-33.pyc
