Metadata-Version: 2.0
Name: django-websocket-request
Version: 0.1.1
Summary: Support for Django's request/response lifecycle to automatically handle WebSocket messages.
Home-page: https://github.com/GetBlimp/django-websocket-request
Author: Jose Padilla
Author-email: jpadilla@getblimp.com
License: MIT
Platform: UNKNOWN
Requires-Dist: Django (>=1.3)
